helloworld.py
helloworld_sujanay-0.0.1.dist-info/METADATA
helloworld_sujanay-0.0.1.dist-info/WHEEL
helloworld_sujanay-0.0.1.dist-info/top_level.txt
helloworld_sujanay-0.0.1.dist-info/RECORD
